<?xml version="1.0"?>
<?xml-stylesheet type="text/xsl" href="apc_ddf_1_6.xsl"?>
<APC_DDF
	xmlns:xsi="http://www.w3.org/2001/XMLSchema-instance"
	xsi:noNamespaceSchemaLocation="http://localhost/ddf_schema/apc_ddf_1_6.xsd"
	ddfid="universal_electric_corp_starline_critical_power_monitor_m21"
	ddfname="Universal Electric Corp Starline Critical Power Monitor M21"
	ddfversion="1"
	canremove="yes">
	<schemaVersion>1.6</schemaVersion>
	<device deviceid="universal_electric_corp_starline_critical_power_monitor_m21">
		<suppressRule ruleid="suppresscorevendordata" suppressid="core/mib2data/vendordata"/>
		<suppressRule ruleid="suppresscoremodeldata" suppressid="core/mib2data/modeldata"/>
		<suppressRule ruleid="suppresscoretypedata" suppressid="core/mib2data/typedata"/>

		<setProductData ruleid="vendordata" field="vendor">Universal Electric Corp</setProductData>
		<setProductData ruleid="modeldata" field="model">Starline Critical Power Monitor M21</setProductData>
		<setProductData ruleid="typedata" field="type">Generic Device</setProductData>

		<oidMustExist ruleid="universal_electric_corp_starline_critical_power_monitor_m21" oid=".1.3.6.1.4.1.35774.1" istree="yes"/>

		<numSensor ruleid="iccAPhase">
			<type>amperage</type>
			<sensorId>ICC_A_PHASE</sensorId>
			<value>
				<mult>
				<op><getOid>.1.3.6.1.4.1.35774.1.1.1.0</getOid></op>
				<op>1</op>
				</mult>
			</value>
			<label>ICC A Phase</label>
			<sensorSet>phase_current</sensorSet>
		</numSensor>
		<numSensor ruleid="iccBPhase">
			<type>amperage</type>
			<sensorId>ICC_B_PHASE</sensorId>
			<value>
				<mult>
				<op><getOid>.1.3.6.1.4.1.35774.1.1.2.0</getOid></op>
				<op>1</op>
				</mult>
			</value>
			<label>ICC B Phase</label>
			<sensorSet>phase_current</sensorSet>
		</numSensor>
		<numSensor ruleid="iccCPhase">
			<type>amperage</type>
			<sensorId>ICC_C_PHASE</sensorId>
			<value>
				<mult>
				<op><getOid>.1.3.6.1.4.1.35774.1.1.3.0</getOid></op>
				<op>1</op>
				</mult>
			</value>
			<label>ICC C Phase</label>
			<sensorSet>phase_current</sensorSet>
		</numSensor>
		<numSensor ruleid="iccNeutral">
			<type>amperage</type>
			<sensorId>ICC_NEUTRAL</sensorId>
			<value>
				<mult>
				<op><getOid>.1.3.6.1.4.1.35774.1.1.4.0</getOid></op>
				<op>1</op>
				</mult>
			</value>
			<label>ICC Neutral</label>
			<sensorSet>phase_current</sensorSet>
		</numSensor>
		<numSensor ruleid="iccAAlarm">
			<type>amperage</type>
			<sensorId>ICC_A_ALARM</sensorId>
			<value>
				<mult>
				<op><getOid>.1.3.6.1.4.1.35774.1.1.5.0</getOid></op>
				<op>1</op>
				</mult>
			</value>
			<label>ICC A Alarm</label>
			<sensorSet>phase_current</sensorSet>
		</numSensor>
		<numSensor ruleid="iccBAlarm">
			<type>amperage</type>
			<sensorId>ICC_B_ALARM</sensorId>
			<value>
				<mult>
				<op><getOid>.1.3.6.1.4.1.35774.1.1.6.0</getOid></op>
				<op>1</op>
				</mult>
			</value>
			<label>ICC B Alarm</label>
			<sensorSet>phase_current</sensorSet>
		</numSensor>
		<numSensor ruleid="iccCAlarm">
			<type>amperage</type>
			<sensorId>ICC_C_ALARM</sensorId>
			<value>
				<mult>
				<op><getOid>.1.3.6.1.4.1.35774.1.1.7.0</getOid></op>
				<op>1</op>
				</mult>
			</value>
			<label>ICC C Alarm</label>
			<sensorSet>phase_current</sensorSet>
		</numSensor>
		<numSensor ruleid="iccNAlarm">
			<type>amperage</type>
			<sensorId>ICC_N_ALARM</sensorId>
			<value>
				<mult>
				<op><getOid>.1.3.6.1.4.1.35774.1.1.8.0</getOid></op>
				<op>1</op>
				</mult>
			</value>
			<label>ICC N Alarm</label>
			<sensorSet>phase_current</sensorSet>
		</numSensor>
		<numSensor ruleid="vacAPhase">
			<type>voltage</type>
			<sensorId>VAC_A_PHASE</sensorId>
			<value>
				<mult>
				<op><getOid>.1.3.6.1.4.1.35774.1.2.1.0</getOid></op>
				<op>1</op>
				</mult>
			</value>
			<label>VAC A Phase</label>
			<sensorSet>phase_voltage</sensorSet>
		</numSensor>
		<numSensor ruleid="vacBPhase">
			<type>voltage</type>
			<sensorId>VAC_B_PHASE</sensorId>
			<value>
				<mult>
				<op><getOid>.1.3.6.1.4.1.35774.1.2.2.0</getOid></op>
				<op>1</op>
				</mult>
			</value>
			<label>VAC B Phase</label>
			<sensorSet>phase_voltage</sensorSet>
		</numSensor>
		<numSensor ruleid="vacCPhase">
			<type>voltage</type>
			<sensorId>VAC_C_PHASE</sensorId>
			<value>
				<mult>
				<op><getOid>.1.3.6.1.4.1.35774.1.2.3.0</getOid></op>
				<op>1</op>
				</mult>
			</value>
			<label>VAC C Phase</label>
			<sensorSet>phase_voltage</sensorSet>
		</numSensor>
		<numSensor ruleid="powerFactor">
			<type>num</type>
			<sensorId>POWER_FACTOR</sensorId>
			<value>
				<mult>
				<op><getOid>.1.3.6.1.4.1.35774.1.3.1.0</getOid></op>
				<op>1</op>
				</mult>
			</value>
			<label>Power Factor</label>
			<sensorSet>power_energy</sensorSet>
		</numSensor>
		<numSensor ruleid="activePower">
			<type>num</type>
			<sensorId>ACTIVE_POWER</sensorId>
			<value>
				<mult>
				<op><getOid>.1.3.6.1.4.1.35774.1.3.2.0</getOid></op>
				<op>1</op>
				</mult>
			</value>
			<label>Active Power</label>
			<sensorSet>power_energy</sensorSet>
		</numSensor>
		<numSensor ruleid="apparentPower">
			<type>num/powerKVA</type>
			<sensorId>APPARENT_POWER</sensorId>
			<value>
				<mult>
				<op><getOid>.1.3.6.1.4.1.35774.1.3.3.0</getOid></op>
				<op>1</op>
				</mult>
			</value>
			<label>Apparent Power</label>
			<sensorSet>power_energy</sensorSet>
		</numSensor>
		<numSensor ruleid="reactivePower">
			<type>num/powerKVAR</type>
			<sensorId>REACTIVE_POWER</sensorId>
			<value>
				<mult>
				<op><getOid>.1.3.6.1.4.1.35774.1.3.4.0</getOid></op>
				<op>1</op>
				</mult>
			</value>
			<label>Reactive Power</label>
			<sensorSet>power_energy</sensorSet>
		</numSensor>
		<numSensor ruleid="notUsed">
			<type>num</type>
			<sensorId>NOT_USED</sensorId>
			<value>
				<mult>
				<op><getOid>.1.3.6.1.4.1.35774.1.3.5.0</getOid></op>
				<op>1</op>
				</mult>
			</value>
			<label>Not Used</label>
			<sensorSet>power_energy</sensorSet>
		</numSensor>
		<numSensor ruleid="meteredEnergy">
			<type>num/kwatthr</type>
			<sensorId>METERED_ENERGY</sensorId>
			<value>
				<mult>
				<op><getOid>.1.3.6.1.4.1.35774.1.3.6.0</getOid></op>
				<op>1</op>
				</mult>
			</value>
			<label>Metered Energy</label>
			<sensorSet>power_energy</sensorSet>
		</numSensor>
		<numSensor ruleid="frequency">
			<type>frequency</type>
			<sensorId>FREQUENCY</sensorId>
			<value>
				<mult>
				<op><getOid>.1.3.6.1.4.1.35774.1.3.7.0</getOid></op>
				<op>1</op>
				</mult>
			</value>
			<label>Frequency</label>
			<sensorSet>power_energy</sensorSet>
		</numSensor>
		<numSensor ruleid="temperature">
			<type>temp</type>
			<sensorId>TEMPERATURE</sensorId>
			<value>
				<mult>
				<op><getOid>.1.3.6.1.4.1.35774.1.4.4.0</getOid></op>
				<op>1</op>
				</mult>
			</value>
			<label>Temperature</label>
			<sensorSet>general_info</sensorSet>
		</numSensor>
		<numSensor ruleid="serialAddress">
			<type>num</type>
			<sensorId>SERIAL_ADDRESS</sensorId>
			<value>
				<mult>
				<op><getOid>.1.3.6.1.4.1.35774.1.4.7.0</getOid></op>
				<op>1</op>
				</mult>
			</value>
			<label>Serial Address</label>
			<sensorSet>general_info</sensorSet>
		</numSensor>
	</device>
</APC_DDF>
